flask_ipfilter/__init__.py
flask_ipfilter/blacklist.py
flask_ipfilter/callback.py
flask_ipfilter/ipfilter.py
flask_ipfilter/whitelist.py
Flask_IPFilter-0.0.5.dist-info/LICENSE.txt
Flask_IPFilter-0.0.5.dist-info/METADATA
Flask_IPFilter-0.0.5.dist-info/WHEEL
Flask_IPFilter-0.0.5.dist-info/top_level.txt
Flask_IPFilter-0.0.5.dist-info/RECORD
